fust_orm-0.1.1.dist-info/METADATA
fust_orm-0.1.1.dist-info/WHEEL
fust_orm-0.1.1.dist-info/licenses/LICENSE
fust_orm/__init__.py
fust_orm/fust_orm.cpython-310-i386-linux-gnu.so
fust_orm/fust_orm.pyi
fust_orm-0.1.1.dist-info/RECORD
