Metadata-Version: 2.4
Name: fust_orm
Version: 0.1.1
Classifier: Programming Language :: Rust
Classifier: Programming Language :: Python :: Implementation :: CPython
Classifier: Programming Language :: Python :: Implementation :: PyPy
Classifier: Programming Language :: Python :: 3
Classifier: Programming Language :: Python :: 3.9
Classifier: Programming Language :: Python :: 3.10
Classifier: Programming Language :: Python :: 3.11
Classifier: Programming Language :: Python :: 3.12
Classifier: Programming Language :: Python :: 3.13
Classifier: License :: OSI Approved :: MIT License
Classifier: Operating System :: OS Independent
Classifier: Intended Audience :: Developers
License-File: LICENSE
Summary: An experimental, blazingly fast, and intuitive asynchronous ORM for Python, written in Rust.
Author-email: dobrotacreator <dobrota.creator@gmail.com>
Maintainer-email: dobrotacreator <dobrota.creator@gmail.com>
License-Expression: MIT
Requires-Python: >=3.9
Project-URL: Repository, https://github.com/dobrotacreator/fust-orm
Project-URL: Issues, https://github.com/dobrotacreator/fust-orm/issues
